filesystem_operations_mcp/__init__.py
filesystem_operations_mcp/logging.py
filesystem_operations_mcp/main.py
filesystem_operations_mcp/filesystem/__init__.py
filesystem_operations_mcp/filesystem/errors.py
filesystem_operations_mcp/filesystem/file_system.py
filesystem_operations_mcp/filesystem/nodes.py
filesystem_operations_mcp/filesystem/view.py
filesystem_operations_mcp/filesystem/detection/file_type.py
filesystem_operations_mcp/filesystem/mappings/magika_to_tree_sitter.py
filesystem_operations_mcp/filesystem/patches/file.py
filesystem_operations_mcp/filesystem/summarize/__init__.py
filesystem_operations_mcp/filesystem/summarize/code.py
filesystem_operations_mcp/filesystem/summarize/markdown.py
filesystem_operations_mcp/filesystem/summarize/text.py
filesystem_operations_mcp/filesystem/summarize/tree-sitter-language-pack/README.md
filesystem_operations_mcp/filesystem/summarize/tree-sitter-language-pack/arduino-tags.scm
filesystem_operations_mcp/filesystem/summarize/tree-sitter-language-pack/c-tags.scm
filesystem_operations_mcp/filesystem/summarize/tree-sitter-language-pack/chatito-tags.scm
filesystem_operations_mcp/filesystem/summarize/tree-sitter-language-pack/commonlisp-tags.scm
filesystem_operations_mcp/filesystem/summarize/tree-sitter-language-pack/cpp-tags.scm
filesystem_operations_mcp/filesystem/summarize/tree-sitter-language-pack/csharp-tags.scm
filesystem_operations_mcp/filesystem/summarize/tree-sitter-language-pack/d-tags.scm
filesystem_operations_mcp/filesystem/summarize/tree-sitter-language-pack/dart-tags.scm
filesystem_operations_mcp/filesystem/summarize/tree-sitter-language-pack/elisp-tags.scm
filesystem_operations_mcp/filesystem/summarize/tree-sitter-language-pack/elixir-tags.scm
filesystem_operations_mcp/filesystem/summarize/tree-sitter-language-pack/elm-tags.scm
filesystem_operations_mcp/filesystem/summarize/tree-sitter-language-pack/gleam-tags.scm
filesystem_operations_mcp/filesystem/summarize/tree-sitter-language-pack/go-tags.scm
filesystem_operations_mcp-0.6.11.dist-info/METADATA
filesystem_operations_mcp-0.6.11.dist-info/WHEEL
filesystem_operations_mcp-0.6.11.dist-info/entry_points.txt
filesystem_operations_mcp-0.6.11.dist-info/RECORD
