Metadata-Version: 2.4
Name: filesystem_operations_mcp
Version: 0.6.11
Summary: Filesystem Operations MCP project
Requires-Python: >=3.13
Requires-Dist: aiofiles>=24.1.0
Requires-Dist: aioshutil>=1.5
Requires-Dist: async-lru>=2.0.5
Requires-Dist: asyncclick>=8.1.8
Requires-Dist: asyncstdlib>=3.13.1
Requires-Dist: fastmcp>2.11.0
Requires-Dist: gitpython>=3.1.45
Requires-Dist: magika>=0.6.2
Requires-Dist: makefun>=1.16.0
Requires-Dist: mcp>=1.9.0
Requires-Dist: mistune>=3.1.3
Requires-Dist: pydantic>=2.10.6
Requires-Dist: pytest-benchmark>=5.1.0
Requires-Dist: pyyaml>=6.0.2
Requires-Dist: ripgrep>=14.1.0
Requires-Dist: rpygrep>=0.1.1
Requires-Dist: sumy>=0.11.0
Requires-Dist: syrupy>=4.9.1
Requires-Dist: tree-sitter-language-pack>=0.7.3
Requires-Dist: tree-sitter>=0.24.0
